Workbook

Sheet Respuestas de formulario 1
A1: Marca temporal | B1: Código del encuestador | C1: Nombre del local | D1: Nacionalidad (Entrevistado/a | E1: Edad | F1: Sexo | G1: A1. En este local¿Compró usted hoy algún medicamento que contenga tirzepatida?: | H1: A1.1. ¿De qué marca? | I1: A1.2. Especificar la marca (Si marcó la opc. Otro) | J1: A2. Este producto fue comprado para: | K1: A3. ¿Con qué frecuencia compra este producto aproximadamente? | L1: B1. ¿Cuál es el principal motivo por el que utiliza tirzepatida? (Respuesta espontánea) | M1: B.1.1. Especificar (Si marcó la opc. Otro) | N1: B2. ¿Cuál fue el factor más importante en su decisión de compra? | O1: B3. ¿Qué información le gustaría recibir sobre este medicamento? | P1: C1. ¿Quién le recomendó/ indicó usar tirzepatida? | Q1: C.1.1. Especificar (Si marcó la opc. Otro) | R1: C2. ¿Cuál fue el factor más importante en su decisión de compra? | S1: C.2.1. Especificar (Si marcó la opc. Otro) | T1: D.1. ¿Cuánto pagó por cada caja? | U1: D.1.1. Unidad Monetaria | V1: D2. ¿Considera que el precio de tirzepatida es:? | W1: A4. ¿En que presentación (en mg) compró hoy? | X1: A.4.1. Especificar (Si marcó la opc. Otra) | Y1: A.5. ¿Esta es la presentación que elije siempre que compra? | Z1: Columna 26 | AA1: Columna 27 | AB1: Columna 28 | AC1: Columna 29 | AD1: Columna 30 | AE1: Columna 31
A2: 46164.551 | B2: 148 | C2: FarmaCon | D2: Brasilera | E2: 37 | F2: Masculino | G2: Sí | H2: Tirzedral | J2: Para un familiar | K2: Ocasionalmente | L2: Recomendación médica general | N2: Recomendación del médico | O2: Seguridad / efectos secundarios | P2: Médico especialista (endocrinólogo / diabetólogo) | R2: Recomendación del médico | T2: 85 | U2: Dolar Americano | V2: Adecuado | W2: 15 mg | Y2: Sí
A3: 46164.552 | B3: 602 | C3: Cell Shopp | D3: Brasilera | E3: 40 | F3: Masculino | G3: Sí | H3: T.G. | J3: Uso propio | K3: Cada mes | L3: Pérdida de peso | N3: Resultados para bajar de peso | O3: Resultados de pérdida de peso, Comparación con otros tratamientos | P3: Médico clínico | R3: Resultados para bajar de peso | T3: 425 | U3: Reales | V3: Barato | W3: 15 mg | Y3: Sí
A4: 46164.553 | B4: 148 | C4: FarmaCon | D4: Brasilera | E4: 39 | F4: Masculino | G4: Sí | H4: Tirzedral | J4: Para un familiar | K4: Ocasionalmente | L4: Recomendación médica general | N4: Recomendación del médico | O4: Seguridad / efectos secundarios | P4: Médico especialista (endocrinólogo / diabetólogo) | R4: Recomendación del médico | T4: 420 | U4: Reales | V4: Adecuado | W4: 15 mg | Y4: Sí
A5: 46164.554 | B5: 602 | C5: Cell Shopp | D5: Brasilera | E5: 38 | F5: Femenino | G5: Sí | H5: T.G. | J5: Uso propio | K5: Cada 2 - 3 meses | L5: Recomendación médica general | N5: Resultados para bajar de peso | O5: Promociones / precio, Recomendaciones de médicos | P5: Médico especialista (endocrinólogo / diabetólogo) | R5: Recomendación del médico | T5: 85 | U5: Dolar Americano | V5: Adecuado | W5: 15 mg | Y5: Sí
A6: 46164.613 | B6: 602 | C6: Cell Shopp | D6: Brasilera | E6: 33 | F6: Femenino | G6: Sí | H6: T.G. | J6: Para un familiar | K6: Ocasionalmente | L6: Recomendación médica general | N6: Recomendación del médico | O6: Promociones / precio | P6: Médico clínico | R6: Recomendación del médico | T6: 83 | U6: Dolar Americano | V6: Adecuado | W6: 15 mg | Y6: Sí
A7: 46164.656 | B7: 148 | C7: FarmaCon | D7: Argentina | E7: 44 | F7: Femenino | G7: Sí | H7: Lipoless | J7: Uso propio | K7: Ocasionalmente | L7: Pérdida de peso | N7: Resultados para bajar de peso | O7: Resultados de pérdida de peso, Seguridad / efectos secundarios, Promociones / precio | P7: Médico especialista (endocrinólogo / diabetólogo) | R7: Resultados para bajar de peso | T7: 77 | U7: Dolar Americano | V7: Caro | W7: 15 mg | Y7: Sí
A8: 46164.658 | B8: 148 | C8: FarmaCon | D8: Argentina | E8: 26 | F8: Femenino | G8: Sí | H8: Lipoless | J8: Uso propio | K8: Ocasionalmente | L8: Pérdida de peso | N8: Resultados para bajar de peso | O8: Resultados de pérdida de peso, Seguridad / efectos secundarios | P8: Decisión propia | R8: Resultados para bajar de peso | T8: 77 | U8: Dolar Americano | V8: Adecuado | W8: 15 mg | Y8: Sí
A9: 46165.403 | B9: 265 | C9: Columbia | D9: Brasilera | E9: 35 | F9: Femenino | G9: Sí | H9: Tirzec | J9: Uso propio | K9: Cada mes | L9: Pérdida de peso | N9: Resultados para bajar de peso | O9: Resultados de pérdida de peso | P9: Redes sociales / internet | R9: Resultados para bajar de peso | T9: 81 | U9: Dolar Americano | V9: Adecuado | W9: 15 mg | Y9: Sí
A10: 46165.514 | B10: 265 | C10: Farma Shop Dior | D10: Brasilera | E10: 48 | F10: Femenino | G10: Sí | H10: T.G. | J10: Uso propio | K10: Ocasionalmente | L10: Pérdida de peso | N10: Resultados para bajar de peso | O10: Resultados de pérdida de peso | P10: Decisión propia | R10: Resultados para bajar de peso | T10: 600000 | U10: Guaraníes | V10: Adecuado | W10: 5 mg | Y10: Sí
A11: 46165.516 | B11: 182 | C11: Triunfo | D11: Brasilera | E11: 41 | F11: Masculino | G11: Sí | H11: T.G. | J11: Uso propio | K11: Cada 2 - 3 meses | L11: Pérdida de peso | N11: Resultados para bajar de peso | O11: Resultados de pérdida de peso | P11: Médico especialista (endocrinólogo / diabetólogo) | R11: Resultados para bajar de peso | T11: 370 | U11: Reales | V11: Barato | W11: 2,5 mg | Y11: Sí
A12: 46165.517 | B12: 265 | C12: Farma Shop Dior | D12: Brasilera | E12: 55 | F12: Femenino | G12: Sí | H12: T.G. | J12: Uso propio | K12: Cada mes | L12: Recomendación médica general | N12: Recomendación del médico | O12: Resultados de pérdida de peso, Seguridad / efectos secundarios, Comparación con otros tratamientos, Promociones / precio, Recomendaciones de médicos | P12: Médico clínico | R12: Recomendación del médico | T12: 900000 | U12: Guaraníes | V12: Caro | W12: 12,5 mg | Y12: Sí
A13: 46165.519 | B13: 265 | C13: Farma Shop Dior | D13: Brasilera | E13: 60 | F13: Masculino | G13: Sí | H13: T.G. | J13: Uso propio | K13: Cada mes | L13: Recomendación médica general | N13: Recomendación del médico | O13: Recomendaciones de médicos | P13: Médico clínico | R13: Recomendación del médico | T13: 900000 | U13: Guaraníes | V13: Adecuado | W13: 12,5 mg | Y13: Sí
... A39: 46167.512 | B39: 148 | C39: ICLINIC | D39: Brasilera | E39: 38 | F39: Masculino | G39: Sí | H39: T.G. | J39: Para un familiar | K39: Cada 2 - 3 meses | L39: Recomendación médica general | N39: Recomendación del médico | O39: Seguridad / efectos secundarios | P39: Médico clínico | R39: Recomendación del médico | T39: 85 | U39: Dolar Americano | V39: Adecuado | W39: 15 mg | Y39: Sí
A40: 46167.513 | B40: 148 | C40: ICLINIC | D40: Brasilera | F40: Femenino | G40: Sí | H40: T.G. | J40: Uso propio | K40: Ocasionalmente | L40: Recomendación médica general | N40: Recomendación del médico | O40: Resultados de pérdida de peso, Seguridad / efectos secundarios | P40: Médico especialista (endocrinólogo / diabetólogo) | R40: Recomendación del médico | T40: 85 | U40: Dolar Americano | V40: Adecuado | W40: 15 mg | Y40: Sí
A41: 46167.514 | B41: 148 | C41: ICLINIC | D41: Brasilera | F41: Masculino | G41: Sí | H41: Lipoless | J41: Uso propio, Para un familiar | K41: Ocasionalmente | L41: Recomendación médica general | N41: Recomendación del médico | O41: Seguridad / efectos secundarios, Promociones / precio | P41: Médico especialista (endocrinólogo / diabetólogo) | R41: Recomendación del médico | T41: 75 | U41: Dolar Americano | V41: Adecuado | W41: 15 mg | Y41: Sí
A42: 46167.517 | B42: 148 | C42: ICLINIC | D42: Brasilera | E42: 32 | F42: Femenino | G42: Sí | H42: Lipoless | J42: Uso propio | K42: Cada 2 - 3 meses | L42: Pérdida de peso | N42: Recomendación del médico | O42: Resultados de pérdida de peso, Seguridad / efectos secundarios | P42: Médico especialista (endocrinólogo / diabetólogo) | R42: Resultados para bajar de peso | T42: 75 | U42: Dolar Americano | V42: Caro | W42: 15 mg | Y42: Sí

Sheet Monitoreo_M(B)_T2.0
A1: COUNTA de A1.1. ¿De qué marca? | B1: A1.1. ¿De qué marca?
A2: Nombre del local | B2: Gluconex | C2: Lipoless | D2: T.G. | E2: Tirzec | F2: Tirzedral | G2: Suma total
A3: Cell Shopp | D3: 4 | G3: 4
A4: Columbia | B4: 3 | C4: 8 | E4: 3 | G4: 14
A5: Farma Shop Dior | C5: 5 | D5: 3 | E5: 3 | G5: 11
A6: FarmaCon | C6: 2 | F6: 2 | G6: 4
A7: ICLINIC | C7: 2 | D7: 2 | G7: 4
A8: Triunfo | D8: 2 | E8: 1 | F8: 1 | G8: 4
A9: Suma total | B9: 3 | C9: 17 | D9: 11 | E9: 7 | F9: 3 | G9: 41
A44: MEDIAN de D.1. ¿Cuánto pagó por cada caja? | B44: D.1.1. Unidad Monetaria
A45: A1.1. ¿De qué marca? | B45: Dolar Americano | C45: Guaraníes | D45: Reales
A46: Gluconex | B46: 85
A47: Lipoless | B47: 75 | C47: 1130000
A48: T.G. | B48: 85 | C48: 900000 | D48: 397.5
A49: Tirzec | B49: 81 | C49: 700000 | D49: 310
A50: Tirzedral | B50: 87 | D50: 420
A51: Suma total | B51: 81 | C51: 850000 | D51: 395
A55: MEDIAN de D.1. ¿Cuánto pagó por cada caja? | B55: A1.1. ¿De qué marca? | C55: D.1.1. Unidad Monetaria
B56: Gluconex | C56: Lipoless | E56: T.G. | H56: Tirzec | K56: Tirzedral
A57: Nombre del local | B57: Dolar Americano | C57: Dolar Americano | D57: Guaraníes | E57: Dolar Americano | F57: Guaraníes | G57: Reales | H57: Dolar Americano | I57: Guaraníes | J57: Reales | K57: Dolar Americano | L57: Reales
A58: Cell Shopp | E58: 83 | G58: 425
A59: Columbia | B59: 85 | C59: 70 | H59: 81
A60: Farma Shop Dior | C60: 120 | D60: 1130000 | F60: 900000 | I60: 700000
A61: FarmaCon | C61: 77 | K61: 85 | L61: 420
A62: ICLINIC | C62: 75 | E62: 85
A63: Triunfo | E63: 87 | G63: 370 | J63: 310 | K63: 89
A64: Suma total | B64: 85 | C64: 75 | D64: 1130000 | E64: 85 | F64: 900000 | G64: 397.5 | H64: 81 | I64: 700000 | J64: 310 | K64: 87 | L64: 420
A86: MEDIAN de D.1. ¿Cuánto pagó por cada caja? | B86: A4. ¿En que presentación (en mg) compró hoy? | C86: D.1.1. Unidad Monetaria
B87: 10 mg | C87: 12,5 mg | D87: 15 mg | G87: 2,5 mg | H87: 5 mg | J87: 7,5 mg
A88: A1.1. ¿De qué marca? | B88: Dolar Americano | C88: Guaraníes | D88: Dolar Americano | E88: Guaraníes | F88: Reales | G88: Reales | H88: Dolar Americano | I88: Guaraníes | J88: Guaraníes
A89: Gluconex | D89: 85
A90: Lipoless | B90: 70 | C90: 1110000 | D90: 77 | E90: 1150000 | H90: 60 | J90: 800000
A91: T.G. | C91: 900000 | D91: 85 | F91: 425 | G91: 370 | H91: 87 | I91: 600000
A92: Tirzec | D92: 81 | G92: 310 | I92: 700000
A93: Tirzedral | D93: 85 | F93: 420 | H93: 89
A94: Suma total | B94: 70 | C94: 900000 | D94: 83 | E94: 1150000 | F94: 422.5 | G94: 340 | H94: 73.5 | I94: 700000 | J94: 800000

Sheet EXTRAPOLACION
A1: Estabelcimientos | B1: Ventas en años | C1: Marcas | D1: Stock | E1: Unidades ( semana) | F1: T. Ventas | G1: IC.Cajas por clientes (dia) | H1: Cajas por clientes (dia) | I1: Cajas por clientes (semana) | J1: Visitas clientes Tir (dia) | K1: Visitas clientesTir (semana) | L1: Costo cajas med ( USD) | M1: Total Cajas (D) | N1: Total Cajas (S) | O1: Total Cajas (M) | P1: Total Cajas (A) | Q1: Total Ventas USD (D) | R1: Total Ventas USD (S) | S1: Total Ventas USD (M) | T1: Total Ventas USD (A) | U1: Total Ventas GS (A) | V1: Orden $
A2: ='Monitoreo_M(B)_T2.0'!A3 -> Cell Shopp | B2: > 3 añ0s | C2: Tirzec, T.G., Gluconex, Lipoless, Lipoland | D2: Estable | E2: =125*6 -> 750 | F2: Aumento | G2: 2 a 5 | H2: 3 | I2: =+H2*6 -> 18 | J2: 30 | K2: =+J2*6 -> 180 | L2: 80 | M2: =+H2*J2 -> 90 | N2: =+M2*6 -> 540 | O2: =+M2*24 -> 2160 | P2: =+O2*12 -> 25920 | Q2: =+$L$2*M2 -> 7200 | R2: =+$L$2*N2 -> 43200 | S2: =+$L$2*O2 -> 172800 | T2: =+$L$2*P2 -> 2073600 | U2: =+T2*7000 -> 14515200000
A3: ='Monitoreo_M(B)_T2.0'!A4 -> Columbia | B3: < 1 año | C3: Tirzec, T.G., Gluconex, Lipoless, Tirzedral | D3: Estable | E3: 40000 | F3: Aumento | G3: 2 a 5 | H3: 3 | I3: =+H3*6 -> 18 | J3: 2000 | K3: =+J3*6 -> 12000 | L3: 90 | M3: =+H3*J3 -> 6000 | N3: =+M3*6 -> 36000 | O3: =+M3*24 -> 144000 | P3: =+O3*12 -> 1728000 | Q3: =+$L$3*M3 -> 540000 | R3: =+$L$3*N3 -> 3240000 | S3: =+$L$3*O3 -> 12960000 | T3: =+$L$3*P3 -> 155520000 | U3: =+T3*7000 -> 1088640000000 | V3: 1
A4: ='Monitoreo_M(B)_T2.0'!A5 -> Farma Shop Dior | B4: > 3 añ0s | C4: Tirzec, T.G., Gluconex, Lipoless, Tirzedral, Lipoland | D4: Estable | E4: =300*8 -> 2400 | F4: Aumento | G4: 7 a 11 | H4: 8.5 | I4: =+H4*6 -> 51 | J4: 50 | K4: =+J4*6 -> 300 | L4: 75 | M4: =+H4*J4 -> 425 | N4: =+M4*6 -> 2550 | O4: =+M4*24 -> 10200 | P4: =+O4*12 -> 122400 | Q4: =+$L$4*M4 -> 31875 | R4: =+$L$4*N4 -> 191250 | S4: =+$L$4*O4 -> 765000 | T4: =+$L$4*P4 -> 9180000 | U4: =+T4*7000 -> 64260000000
A5: ='Monitoreo_M(B)_T2.0'!A6 -> FarmaCon | B5: < 1 año | C5: Tirzec, T.G., Gluconex, Lipoless, | D5: Estable | E5: 840 | F5: Aumento | G5: 2 a 5 | H5: 3 | I5: =+H5*6 -> 18 | J5: 180 | K5: =+J5*6 -> 1080 | L5: 85 | M5: =+H5*J5 -> 540 | N5: =+M5*6 -> 3240 | O5: =+M5*24 -> 12960 | P5: =+O5*12 -> 155520 | Q5: =+$L$5*M5 -> 45900 | R5: =+$L$5*N5 -> 275400 | S5: =+$L$5*O5 -> 1101600 | T5: =+$L$5*P5 -> 13219200 | U5: =+T5*7000 -> 92534400000
A6: ='Monitoreo_M(B)_T2.0'!A7 -> ICLINIC | B6: < 1 año | C6: Tirzec, T.G., Gluconex, Lipoless, Tirzedral | D6: Estable | E6: 2100 | F6: Aumento | G6: 1 | H6: 1 | I6: =+H6*6 -> 6 | J6: 550 | K6: =+J6*6 -> 3300 | L6: 87 | M6: =+H6*J6 -> 550 | N6: =+M6*6 -> 3300 | O6: =+M6*24 -> 13200 | P6: =+O6*12 -> 158400 | Q6: =+$L$6*M6 -> 47850 | R6: =+$L$6*N6 -> 287100 | S6: =+$L$6*O6 -> 1148400 | T6: =+$L$6*P6 -> 13780800 | U6: =+T6*7000 -> 96465600000
B7: < 1 año | C7: Tirzec, T.G., Gluconex, Lipoless, Tirzedral | D7: Escasez (1 semana x mes) | E7: 1500 | F7: Aumento | G7: 2 a 5 | H7: 3 | I7: =+H7*6 -> 18 | J7: 200 | K7: =+J7*6 -> 1200 | L7: 89 | M7: =+H7*J7 -> 600 | N7: =+M7*6 -> 3600 | O7: =+M7*24 -> 14400 | P7: =+O7*12 -> 172800 | Q7: =+$L$7*M7 -> 53400 | R7: =+$L$7*N7 -> 320400 | S7: =+$L$7*O7 -> 1281600 | T7: =+$L$7*P7 -> 15379200 | U7: =+T7*7000 -> 107654400000
B8: < 1 año | C8: Tirzec, T.G., Gluconex, Lipoless, Tirzedral | D8: Estable | E8: 3000 | F8: Mantiene | G8: 2 a 5 | H8: 3 | I8: =+H8*6 -> 18 | J8: 500 | K8: =+J8*6 -> 3000 | L8: 90 | M8: =+H8*J8 -> 1500 | N8: =+M8*6 -> 9000 | O8: =+M8*24 -> 36000 | P8: =+O8*12 -> 432000 | Q8: =+$L$8*M8 -> 135000 | R8: =+$L$8*N8 -> 810000 | S8: =+$L$8*O8 -> 3240000 | T8: =+$L$8*P8 -> 38880000 | U8: =+T8*7000 -> 272160000000 | V8: 2
E9: =SUM(E2:E8) -> 50590 | M9: =SUM(M2:M8) -> 9705 | N9: =SUM(N2:N8) -> 58230 | S9: =SUM(S2:S8) -> 20669400 | T9: =SUM(T2:T8) -> 248032800 | U9: =SUM(U2:U8) -> 1736229600000
A10: MEDIA | H10: =AVERAGE(H2:H8) -> 3.5 | I10: =AVERAGE(I2:I8) -> 21 | J10: =AVERAGE(J2:J8) -> 501.42857 | K10: =AVERAGE(K2:K8) -> 3008.5714 | L10: =AVERAGE(L2:L8) -> 85.142857 | M10: =AVERAGE(M2:M8) -> 1386.4286 | N10: =AVERAGE(N2:N8) -> 8318.5714 | O10: =AVERAGE(O2:O8) -> 33274.286 | ... T10: =AVERAGE(T2:T8) -> 35433257
Q11: {=AVERAGE((Q4:Q8)+Q2)} -> 70005 | R11: {=AVERAGE((R4:R8)+R2)} -> 420030 | S11: {=AVERAGE((S4:S8)+S2)} -> 1680120 | T11: {=AVERAGE((T4:T8)+T2)} -> 20161440
A12: CDE. Farmacias MG*50 | B12: 21 | H12: 4 | J12: =+M12/H12 -> 7599.0441 | K12: =+J12*6 -> 45594.265 | L12: 85 | M12: =+Q12/L12 -> 30396.176 | N12: =+M12*6 -> 182377.06 | O12: =+M12*24 -> 729508.24 | P12: =+O12*10 -> 7295082.4 | Q12: =+$B$12*Q10 -> 2583675 | R12: =+$B$12*R10 -> 15502050 | S12: =+$B$12*S10 -> 62008200 | T12: =+$B$12*T10 -> 744098400 | U12: =+T12*7300 -> 5431918320000
A13: CDE. Farmacias MG*51 | B13: 21 | H13: 4 | J13: =+M13/H13 -> 4323.8382 | K13: =+J13*6 -> 25943.029 | L13: 85 | M13: =+Q13/L13 -> 17295.353 | N13: =+M13*6 -> 103772.12 | O13: =+M13*24 -> 415088.47 | P13: =+O13*11 -> 4565973.2 | Q13: =+$B$12*Q11 -> 1470105 | R13: =+$B$12*R11 -> 8820630 | S13: =+$B$12*S11 -> 35282520 | T13: =+$B$13*T11 -> 423390240 | U13: =+T13*7300 -> 3090748752000
A14: CDE. Turistas
A15: CDE. Ventas
A16: *Proveedor de pequeñas farmacias | M16: =+H12*J12 -> 30396.176
C18: Peso por clientes (dia) | J18: Cajas por clientes (dia) | Q18: Total Cajas (D) | X18: Total Cajas (M) | AE18: Total Ventas USD (D) | AL18: Total Ventas USD (S) | AS18: Total Ventas USD (M) | AZ18: Total Ventas USD (A)
A19: Marcas | B19: Ventas (peso cliente) | C19: Farmacia Pink | D19: Cellshop | E19: Farmacia Brasil | F19: Farmacia Do Sul | G19: Farmacia Columbia | H19: Shopping China | I19: Farmacia Triunfo | J19: Farmacia Pink | K19: Cellshop | L19: Farmacia Brasil | M19: Farmacia Do Sul | N19: Farmacia Columbia | O19: Shopping China | P19: Farmacia Triunfo | Q19: Farmacia Pink | R19: Cellshop | S19: Farmacia Brasil | T19: Farmacia Do Sul | U19: Farmacia Columbia | V19: Shopping China | W19: Farmacia Triunfo | X19: Farmacia Pink | Y19: Cellshop | Z19: Farmacia Brasil | AA19: Farmacia Do Sul | AB19: Farmacia Columbia | AC19: Shopping China | AD19: Farmacia Triunfo | AE19: Farmacia Pink | AF19: Cellshop | AG19: Farmacia Brasil | AH19: Farmacia Do Sul | AI19: Farmacia Columbia | AJ19: Shopping China | AK19: Farmacia Triunfo | AL19: Farmacia Pink | AM19: Cellshop | AN19: Farmacia Brasil | AO19: Farmacia Do Sul | AP19: Farmacia Columbia | AQ19: Shopping China | AR19: Farmacia Triunfo | AS19: Farmacia Pink | AT19: Cellshop | AU19: Farmacia Brasil | AV19: Farmacia Do Sul | AW19: Farmacia Columbia | AX19: Shopping China | AY19: Farmacia Triunfo | AZ19: Farmacia Pink | BA19: Cellshop | BB19: Farmacia Brasil | BC19: Farmacia Do Sul | BD19: Farmacia Columbia | BE19: Shopping China | BF19: Farmacia Triunfo
A20: Gluconex | B20: 0.021126761 | C20: 0 | D20: 0.048780488 | E20: 0 | F20: 0.025 | G20: 0.05 | H20: 0 | I20: 0.023809524 | J20: =+C20*$H$2 -> 0 | K20: =+D20*$H$3 -> 0.14634146 | L20: =+E20*$H$4 -> 0 | M20: =+F20*$H$5 -> 0.075 | N20: =+G20*$H$6 -> 0.05 | O20: =+H20*$H$7 -> 0 | P20: =+I20*$H$8 -> 0.071428572 | Q20: =+C20*$M$2 -> 0 | R20: =+D20*$M$3 -> 292.68293 | S20: =+E20*$M$4 -> 0 | T20: =+F20*$M$5 -> 13.5 | U20: =+G20*$M$7 -> 30 | V20: =+H20*$M$7 -> 0 | W20: =+I20*$M$8 -> 35.714286 | X20: =+C20*$O$2 -> 0 | Y20: =+D20*$O$3 -> 7024.3903 | Z20: =+E20*$O$4 -> 0 | AA20: =+F20*$O$5 -> 324 | AB20: =+G20*$O$6 -> 660 | AC20: =+H20*$O$7 -> 0 | AD20: =+I20*$O$8 -> 857.14286 | AE20: =+C20*$Q$2 -> 0 | AF20: =+D20*$Q$3 -> 26341.464 | AG20: =+E20*$Q$4 -> 0 | AH20: =+F20*$Q$5 -> 1147.5 | AI20: =+G20*$Q$6 -> 2392.5 | AJ20: =+H20*$Q$7 -> 0 | AK20: =+I20*$Q$8 -> 3214.2857 | AL20: =+C20*$R$2 -> 0 | AM20: =+D20*$R$3 -> 158048.78 | AN20: =+E20*$R$4 -> 0 | AO20: =+F20*$R$5 -> 6885 | AP20: =+G20*$R$6 -> 14355 | AQ20: =+H20*$R$7 -> 0 | AR20: =+I20*$R$8 -> 19285.714 | AS20: =+C20*$S$2 -> 0 | AT20: =+D20*$S$3 -> 632195.12 | AU20: =+E20*$S$4 -> 0 | AV20: =+F20*$S$5 -> 27540 | AW20: =+G20*$S$6 -> 57420 | AX20: =+H20*$S$7 -> 0 | AY20: =+I20*$S$8 -> 77142.858 | AZ20: =+C20*$T$2 -> 0 | BA20: =+D20*$T$3 -> 7586341.5 | BB20: =+E20*$T$4 -> 0 | BC20: =+F20*$T$5 -> 330480 | BD20: =+G20*$T$6 -> 689040 | BE20: =+H20*$T$7 -> 0 | BF20: =+I20*$T$8 -> 925714.29
A21: Lipoland | B21: 0.003521127 | C21: 0.024390244 | D21: 0 | E21: 0 | F21: 0 | G21: 0 | H21: 0 | I21: 0 | J21: =+C21*$H$2 -> 0.073170732 | K21: =+D21*$H$3 -> 0 | L21: =+E21*$H$4 -> 0 | M21: =+F21*$H$5 -> 0 | N21: =+G21*$H$6 -> 0 | O21: =+H21*$H$7 -> 0 | P21: =+I21*$H$8 -> 0 | Q21: =+C21*$M$2 -> 2.195122 | R21: =+D21*$M$3 -> 0 | S21: =+E21*$M$4 -> 0 | T21: =+F21*$M$5 -> 0 | U21: =+G21*$M$6 -> 0 | V21: =+H21*$M$7 -> 0 | W21: =+I21*$M$8 -> 0 | X21: =+C21*$O$2 -> 52.682927 | Y21: =+D21*$O$3 -> 0 | Z21: =+E21*$O$4 -> 0 | AA21: =+F21*$O$5 -> 0 | AB21: =+G21*$O$6 -> 0 | AC21: =+H21*$O$7 -> 0 | AD21: =+I21*$O$8 -> 0 | AE21: =+C21*$Q$2 -> 175.60976 | AF21: =+D21*$Q$3 -> 0 | AG21: =+E21*$Q$4 -> 0 | AH21: =+F21*$Q$5 -> 0 | AI21: =+G21*$Q$6 -> 0 | AJ21: =+H21*$Q$7 -> 0 | AK21: =+I21*$Q$8 -> 0 | AL21: =+C21*$R$2 -> 1053.6585 | AM21: =+D21*$R$3 -> 0 | AN21: =+E21*$R$4 -> 0 | AO21: =+F21*$R$5 -> 0 | AP21: =+G21*$R$6 -> 0 | AQ21: =+H21*$R$7 -> 0 | AR21: =+I21*$R$8 -> 0 | AS21: =+C21*$S$2 -> 4214.6342 | AT21: =+D21*$S$3 -> 0 | AU21: =+E21*$S$4 -> 0 | AV21: =+F21*$S$5 -> 0 | AW21: =+G21*$S$6 -> 0 | AX21: =+H21*$S$7 -> 0 | AY21: =+I21*$S$8 -> 0 | AZ21: =+C21*$T$2 -> 50575.61 | BA21: =+D21*$T$3 -> 0 | BB21: =+E21*$T$4 -> 0 | BC21: =+F21*$T$5 -> 0 | BD21: =+G21*$T$6 -> 0 | BE21: =+H21*$T$7 -> 0 | BF21: =+I21*$T$8 -> 0
A22: Lipoless | B22: 0.32042254 | C22: 0.56097561 | D22: 0.29268293 | E22: 0.425 | F22: 0.1 | G22: 0.05 | H22: 0.625 | I22: 0.19047619 | J22: =+C22*$H$2 -> 1.6829268 | K22: =+D22*$H$3 -> 0.87804878 | L22: =+E22*$H$4 -> 3.6125 | M22: =+F22*$H$5 -> 0.3 | N22: =+G22*$H$6 -> 0.05 | O22: =+H22*$H$7 -> 1.875 | P22: =+I22*$H$8 -> 0.57142857 | Q22: =+C22*$M$2 -> 50.487805 | R22: =+D22*$M$3 -> 1756.0976 | S22: =+E22*$M$4 -> 180.625 | T22: =+F22*$M$5 -> 54 | U22: =+G22*$M$6 -> 27.5 | V22: =+H22*$M$7 -> 375 | W22: =+I22*$M$8 -> 285.71429 | X22: =+C22*$O$2 -> 1211.7073 | Y22: =+D22*$O$3 -> 42146.341 | Z22: =+E22*$O$4 -> 4335 | AA22: =+F22*$O$5 -> 1296 | AB22: =+G22*$O$6 -> 660 | AC22: =+H22*$O$7 -> 9000 | AD22: =+I22*$O$8 -> 6857.1428 | AE22: =+C22*$Q$2 -> 4039.0244 | AF22: =+D22*$Q$3 -> 158048.78 | AG22: =+E22*$Q$4 -> 13546.875 | AH22: =+F22*$Q$5 -> 4590 | AI22: =+G22*$Q$6 -> 2392.5 | AJ22: =+H22*$Q$7 -> 33375 | AK22: =+I22*$Q$8 -> 25714.286 | AL22: =+C22*$R$2 -> 24234.146 | AM22: =+D22*$R$3 -> 948292.68 | AN22: =+E22*$R$4 -> 81281.25 | AO22: =+F22*$R$5 -> 27540 | AP22: =+G22*$R$6 -> 14355 | AQ22: =+H22*$R$7 -> 200250 | AR22: =+I22*$R$8 -> 154285.71 | AS22: =+C22*$S$2 -> 96936.585 | AT22: =+D22*$S$3 -> 3793170.7 | AU22: =+E22*$S$4 -> 325125 | AV22: =+F22*$S$5 -> 110160 | AW22: =+G22*$S$6 -> 57420 | AX22: =+H22*$S$7 -> 801000 | AY22: =+I22*$S$8 -> 617142.86 | AZ22: =+C22*$T$2 -> 1163239 | BA22: =+D22*$T$3 -> 45518049 | BB22: =+E22*$T$4 -> 3901500 | BC22: =+F22*$T$5 -> 1321920 | BD22: =+G22*$T$6 -> 689040 | BE22: =+H22*$T$7 -> 9612000 | BF22: =+I22*$T$8 -> 7405714.3
A23: T.G. | B23: 0.35915493 | C23: 0.12195122 | D23: 0.43902439 | E23: 0.375 | F23: 0.725 | G23: 0.175 | H23: 0.225 | I23: 0.45238095 | J23: =+C23*$H$2 -> 0.36585366 | K23: =+D23*$H$3 -> 1.3170732 | L23: =+E23*$H$4 -> 3.1875 | M23: =+F23*$H$5 -> 2.175 | N23: =+G23*$H$6 -> 0.175 | O23: =+H23*$H$7 -> 0.675 | P23: =+I23*$H$8 -> 1.3571429 | Q23: =+C23*$M$2 -> 10.97561 | R23: =+D23*$M$3 -> 2634.1463 | S23: =+E23*$M$4 -> 159.375 | T23: =+F23*$M$5 -> 391.5 | U23: =+G23*$M$6 -> 96.25 | V23: =+H23*$M$7 -> 135 | W23: =+I23*$M$8 -> 678.57143 | X23: =+C23*$O$2 -> 263.41464 | Y23: =+D23*$O$3 -> 63219.512 | Z23: =+E23*$O$4 -> 3825 | AA23: =+F23*$O$5 -> 9396 | AB23: =+G23*$O$6 -> 2310 | AC23: =+H23*$O$7 -> 3240 | AD23: =+I23*$O$8 -> 16285.714 | AE23: =+C23*$Q$2 -> 878.04878 | AF23: =+D23*$Q$3 -> 237073.17 | AG23: =+E23*$Q$4 -> 11953.125 | AH23: =+F23*$Q$5 -> 33277.5 | AI23: =+G23*$Q$6 -> 8373.75 | AJ23: =+H23*$Q$7 -> 12015 | AK23: =+I23*$Q$8 -> 61071.429 | AL23: =+C23*$R$2 -> 5268.2927 | AM23: =+D23*$R$3 -> 1422439 | AN23: =+E23*$R$4 -> 71718.75 | AO23: =+F23*$R$5 -> 199665 | AP23: =+G23*$R$6 -> 50242.5 | AQ23: =+H23*$R$7 -> 72090 | AR23: =+I23*$R$8 -> 366428.57 | AS23: =+C23*$S$2 -> 21073.171 | AT23: =+D23*$S$3 -> 5689756.1 | AU23: =+E23*$S$4 -> 286875 | AV23: =+F23*$S$5 -> 798660 | AW23: =+G23*$S$6 -> 200970 | AX23: =+H23*$S$7 -> 288360 | AY23: =+I23*$S$8 -> 1465714.3 | AZ23: =+C23*$T$2 -> 252878.05 | BA23: =+D23*$T$3 -> 68277073 | BB23: =+E23*$T$4 -> 3442500 | BC23: =+F23*$T$5 -> 9583920 | BD23: =+G23*$T$6 -> 2411640 | BE23: =+H23*$T$7 -> 3460320 | BF23: =+I23*$T$8 -> 17588571
A24: Tirzec | B24: 0.20422535 | C24: 0.29268293 | D24: 0.073170732 | E24: 0.075 | F24: 0.15 | G24: 0.425 | H24: 0.125 | I24: 0.28571429 | J24: =+C24*$H$2 -> 0.87804878 | K24: =+D24*$H$3 -> 0.2195122 | L24: =+E24*$H$4 -> 0.6375 | M24: =+F24*$H$5 -> 0.45 | N24: =+G24*$H$6 -> 0.425 | O24: =+H24*$H$7 -> 0.375 | P24: =+I24*$H$8 -> 0.85714286 | Q24: =+C24*$M$2 -> 26.341463 | R24: =+D24*$M$3 -> 439.02439 | S24: =+E24*$M$4 -> 31.875 | T24: =+F24*$M$5 -> 81 | U24: =+G24*$M$6 -> 233.75 | V24: =+H24*$M$7 -> 75 | W24: =+I24*$M$8 -> 428.57143 | X24: =+C24*$O$2 -> 632.19512 | Y24: =+D24*$O$3 -> 10536.585 | Z24: =+E24*$O$4 -> 765 | AA24: =+F24*$O$5 -> 1944 | AB24: =+G24*$O$6 -> 5610 | AC24: =+H24*$O$7 -> 1800 | AD24: =+I24*$O$8 -> 10285.714 | AE24: =+C24*$Q$2 -> 2107.3171 | AF24: =+D24*$Q$3 -> 39512.195 | AG24: =+E24*$Q$4 -> 2390.625 | AH24: =+F24*$Q$5 -> 6885 | AI24: =+G24*$Q$6 -> 20336.25 | AJ24: =+H24*$Q$7 -> 6675 | AK24: =+I24*$Q$8 -> 38571.429 | AL24: =+C24*$R$2 -> 12643.902 | AM24: =+D24*$R$3 -> 237073.17 | AN24: =+E24*$R$4 -> 14343.75 | AO24: =+F24*$R$5 -> 41310 | AP24: =+G24*$R$6 -> 122017.5 | AQ24: =+H24*$R$7 -> 40050 | AR24: =+I24*$R$8 -> 231428.57 | AS24: =+C24*$S$2 -> 50575.61 | AT24: =+D24*$S$3 -> 948292.69 | AU24: =+E24*$S$4 -> 57375 | AV24: =+F24*$S$5 -> 165240 | AW24: =+G24*$S$6 -> 488070 | AX24: =+H24*$S$7 -> 160200 | AY24: =+I24*$S$8 -> 925714.29 | AZ24: =+C24*$T$2 -> 606907.32 | BA24: =+D24*$T$3 -> 11379512 | BB24: =+E24*$T$4 -> 688500 | BC24: =+F24*$T$5 -> 1982880 | BD24: =+G24*$T$6 -> 5856840 | BE24: =+H24*$T$7 -> 1922400 | BF24: =+I24*$T$8 -> 11108571
A25: Tirzedral | B25: 0.088028169 | C25: 0 | D25: 0.14634146 | E25: 0.125 | F25: 0 | G25: 0.275 | H25: 0.025 | I25: 0.047619048 | J25: =+C25*$H$2 -> 0 | K25: =+D25*$H$3 -> 0.43902439 | L25: =+E25*$H$4 -> 1.0625 | M25: =+F25*$H$5 -> 0 | N25: =+G25*$H$6 -> 0.275 | O25: =+H25*$H$7 -> 0.075 | P25: =+I25*$H$8 -> 0.14285714 | Q25: =+C25*$M$2 -> 0 | R25: =+D25*$M$3 -> 878.04878 | S25: =+E25*$M$4 -> 53.125 | T25: =+F25*$M$5 -> 0 | U25: =+G25*$M$6 -> 151.25 | V25: =+H25*$M$7 -> 15 | W25: =+I25*$M$8 -> 71.428572 | X25: =+C25*$O$2 -> 0 | Y25: =+D25*$O$3 -> 21073.171 | Z25: =+E25*$O$4 -> 1275 | AA25: =+F25*$O$5 -> 0 | AB25: =+G25*$O$6 -> 3630 | AC25: =+H25*$O$7 -> 360 | AD25: =+I25*$O$8 -> 1714.2857 | AE25: =+C25*$Q$2 -> 0 | AF25: =+D25*$Q$3 -> 79024.39 | AG25: =+E25*$Q$4 -> 3984.375 | AH25: =+F25*$Q$5 -> 0 | AI25: =+G25*$Q$6 -> 13158.75 | AJ25: =+H25*$Q$7 -> 1335 | AK25: =+I25*$Q$8 -> 6428.5715 | AL25: =+C25*$R$2 -> 0 | AM25: =+D25*$R$3 -> 474146.34 | AN25: =+E25*$R$4 -> 23906.25 | AO25: =+F25*$R$5 -> 0 | AP25: =+G25*$R$6 -> 78952.5 | AQ25: =+H25*$R$7 -> 8010 | AR25: =+I25*$R$8 -> 38571.429 | AS25: =+C25*$S$2 -> 0 | AT25: =+D25*$S$3 -> 1896585.4 | AU25: =+E25*$S$4 -> 95625 | AV25: =+F25*$S$5 -> 0 | AW25: =+G25*$S$6 -> 315810 | AX25: =+H25*$S$7 -> 32040 | AY25: =+I25*$S$8 -> 154285.72 | AZ25: =+C25*$T$2 -> 0 | BA25: =+D25*$T$3 -> 22759024 | BB25: =+E25*$T$4 -> 1147500 | BC25: =+F25*$T$5 -> 0 | BD25: =+G25*$T$6 -> 3789720 | BE25: =+H25*$T$7 -> 384480 | BF25: =+I25*$T$8 -> 1851428.6
A26: TirzseBound | B26: 0.003521127 | C26: 0 | D26: 0 | E26: 0 | F26: 0 | G26: 0.025 | H26: 0 | I26: 0 | J26: =+C26*$H$2 -> 0 | K26: =+D26*$H$3 -> 0 | L26: =+E26*$H$4 -> 0 | M26: =+F26*$H$5 -> 0 | N26: =+G26*$H$6 -> 0.025 | O26: =+H26*$H$7 -> 0 | P26: =+I26*$H$8 -> 0 | Q26: =+C26*$M$2 -> 0 | R26: =+D26*$M$3 -> 0 | S26: =+E26*$M$4 -> 0 | T26: =+F26*$M$5 -> 0 | U26: =+G26*$M$6 -> 13.75 | V26: =+H26*$M$7 -> 0 | W26: =+I26*$M$8 -> 0 | X26: =+C26*$O$2 -> 0 | Y26: =+D26*$O$3 -> 0 | Z26: =+E26*$O$4 -> 0 | AA26: =+F26*$O$5 -> 0 | AB26: =+G26*$O$6 -> 330 | AC26: =+H26*$O$7 -> 0 | AD26: =+I26*$O$8 -> 0 | AE26: =+C26*$Q$2 -> 0 | AF26: =+D26*$Q$3 -> 0 | AG26: =+E26*$Q$4 -> 0 | AH26: =+F26*$Q$5 -> 0 | AI26: =+G26*$Q$6 -> 1196.25 | AJ26: =+H26*$Q$7 -> 0 | AK26: =+I26*$Q$8 -> 0 | AL26: =+C26*$R$2 -> 0 | AM26: =+D26*$R$3 -> 0 | AN26: =+E26*$R$4 -> 0 | AO26: =+F26*$R$5 -> 0 | AP26: =+G26*$R$6 -> 7177.5 | AQ26: =+H26*$R$7 -> 0 | AR26: =+I26*$R$8 -> 0 | AS26: =+C26*$S$2 -> 0 | AT26: =+D26*$S$3 -> 0 | AU26: =+E26*$S$4 -> 0 | AV26: =+F26*$S$5 -> 0 | AW26: =+G26*$S$6 -> 28710 | AX26: =+H26*$S$7 -> 0 | AY26: =+I26*$S$8 -> 0 | AZ26: =+C26*$T$2 -> 0 | BA26: =+D26*$T$3 -> 0 | BB26: =+E26*$T$4 -> 0 | BC26: =+F26*$T$5 -> 0 | BD26: =+G26*$T$6 -> 344520 | BE26: =+H26*$T$7 -> 0 | BF26: =+I26*$T$8 -> 0
C27: 41 | D27: 41 | E27: 40 | F27: 40 | G27: 40 | H27: 40 | I27: 42 | AE27: =SUM(AE20:AE26) -> 7200 | AF27: =SUM(AF20:AF26) -> 540000 | AG27: =SUM(AG20:AG26) -> 31875 | AH27: =SUM(AH20:AH26) -> 45900 | AI27: =SUM(AI20:AI26) -> 47850 | AJ27: =SUM(AJ20:AJ26) -> 53400 | AK27: =SUM(AK20:AK26) -> 135000 | AL27: =SUM(AL20:AL26) -> 43200 | ... BF27: =SUM(BF20:BF26) -> 38880000
F31: *AJUATAMOS DESDE LA SEGUNDA SEMANA*
